{
  "reviews": {
    "review": [
      {
        "total_rating": {
          "_text": "5"
        },
        "summary": {
          "_cdata": "Wszystko ok"
        }
      },
      {
        "total_rating": {
          "_text": "5"
        },
        "summary": {
          "_cdata": "SUPER"
        }
      },
      {
        "total_rating": {
          "_text": "5"
        },
        "summary": {
          "_cdata": "Zamówienie szybko dotarło. Polecam"
        }
      },
      {
        "total_rating": {
          "_text": "5"
        },
        "summary": {
          "_cdata": "Towar który otzymałem spełnia moje oczekiwania."
        }
      },
      {
        "total_rating": {
          "_text": "5"
        },
        "summary": {
          "_cdata": "Wszystko ok 👍"
        }
      },
      {
        "total_rating": {
          "_text": "5"
        },
        "summary": {
          "_cdata": "Paczka przyszła szybko . Wszystko ok."
        }
      },
      {
        "total_rating": {
          "_text": "5"
        },
        "summary": {
          "_cdata": "Szybka obsługa, doceniam:)"
        }
      },
      {
        "total_rating": {
          "_text": "5"
        },
        "summary": {
          "_cdata": "Wszystko szybko i sprawnie"
        }
      },
      {
        "total_rating": {
          "_text": "5"
        },
        "summary": {
          "_cdata": "Polecam"
        }
      },
      {
        "total_rating": {
          "_text": "5"
        },
        "summary": {
          "_cdata": "Produkt zgodny z opisem."
        }
      },
      {
        "total_rating": {
          "_text": "5"
        },
        "summary": {
          "_cdata": "Wszystko ok"
        }
      },
      {
        "total_rating": {
          "_text": "5"
        },
        "summary": {
          "_cdata": "Ciekawe produkty, szybka wysyłka, dobrze zapakowane."
        }
      },
      {
        "total_rating": {
          "_text": "5"
        },
        "summary": {
          "_cdata": "Polecam"
        }
      },
      {
        "total_rating": {
          "_text": "5"
        },
        "summary": {
          "_cdata": "Polecam"
        }
      },
      {
        "total_rating": {
          "_text": "5"
        },
        "summary": {
          "_cdata": "zamówienie realizowane szybko i w dobrej cenie"
        }
      },
      {
        "total_rating": {
          "_text": "5"
        },
        "summary": {
          "_cdata": "Wszystko w porządku"
        }
      }
    ]
  }
}